revolution/__init__.py
revolution/__version__.py
revolution/colors.py
revolution/constants.py
revolution/revolution.py
revolution/spinner.py
revolution/visual_example.py
tests/__init__.py
tests/test_colors.py
tests/test_revolution.py
tests/test_spinner.py
revolution-0.3.0.dist-info/LICENSE
revolution-0.3.0.dist-info/METADATA
revolution-0.3.0.dist-info/WHEEL
revolution-0.3.0.dist-info/entry_points.txt
revolution-0.3.0.dist-info/top_level.txt
revolution-0.3.0.dist-info/RECORD
