Metadata-Version: 2.1
Name: revolution
Version: 0.3.0
Summary: An assortment of spinners to use while your Python programs run.
Home-page: https://github.com/GBS3/revolution
Author: Giovanni Salinas
Author-email: gbs3@protonmail.com
License: MIT
Project-URL: Source, https://github.com/GBS3/revolution
Keywords: spinner,progress,iterations
Platform: UNKNOWN
Classifier: Development Status :: 4 - Beta
Classifier: Programming Language :: Python :: 3.6
Classifier: Programming Language :: Python :: 3.7
Classifier: Programming Language :: Python :: 3.8
Classifier: Programming Language :: Python :: 3.9
Classifier: License :: OSI Approved :: MIT License
Classifier: Operating System :: OS Independent
